{
  "items": [
    { "1": 5128 },
    { "2": 5135 },
    { "3": 5128 },
    { "4": 5131 },
    { "5": 5131 },
    { "6": 5135 },
    { "7": 5138 },
    { "8": 5138 },
    { "9": 5138 },
    { "10": 5187 },
    { "11": 5097 },
    { "12": 5144 },
    { "13": 5144 },
    { "14": 5169 },
    { "15": 5149 },
    { "16": 5144 },
    { "17": 21029 },
    { "18": 21025 },
    { "19": 5649 },
    { "20": 5157 },
    { "21": 5344 },
    { "22": 5164 },
    { "23": 5202 },
    { "24": 5185 },
    { "25": 5178 },
    { "26": 5649 },
    { "27": 5185 },
    { "28": 5142 },
    { "29": 5161 },
    { "30": 21030 },
    { "31": 5171 },
    { "32": 5171 },
    { "33": 5128 },
    { "34": 21026 },
    { "35": 5649 },
    { "36": 5185 },
    { "37": 5649 },
    { "38": 5185 },
    { "39": 5171 },
    { "40": 5131 },
    { "41": 5138 },
    { "42": 5131 },
    { "43": 5164 },
    { "44": 5174 },
    { "45": 5161 },
    { "46": 5203 },
    { "47": 5205 },
    { "48": 5157 },
    { "49": 5157 },
    { "50": 5157 },
    { "51": 5135 }
  ]
}
